{
	"name": "AzureDataLakeStorage_Source",
	"properties": {
		"annotations": [],
		"type": "AzureBlobFS",
		"typeProperties": {
			"url": "https://gcodersdatalakesource001.dfs.core.windows.net/",
			"tenant": "0dd3c580-c3c7-41f5-a0e2-e6e32dc0a616",
			"servicePrincipalId": "14ea61e7-df87-4867-bd9c-c9fcc24bd517",
			"servicePrincipalCredentialType": "ServicePrincipalKey",
			"servicePrincipalCredential": {
				"type": "AzureKeyVaultSecret",
				"store": {
					"referenceName": "AzureKeyVault1",
					"type": "LinkedServiceReference"
				},
				"secretName": "data-app-secret"
			}
		}
	},
	"type": "Microsoft.DataFactory/factories/linkedservices"
}